bolt_native_macros/__init__.py
bolt_native_macros/aegis.py
bolt_native_macros/ast.py
bolt_native_macros/codegen.py
bolt_native_macros/parse.py
bolt_native_macros/patches.py
bolt_native_macros/plugin.py
bolt_native_macros/serialize.py
bolt_native_macros/typing.py
bolt_native_macros-0.5.1.dist-info/WHEEL
bolt_native_macros-0.5.1.dist-info/METADATA
bolt_native_macros-0.5.1.dist-info/RECORD
