Metadata-Version: 2.3
Name: bolt-native-macros
Version: 0.5.1
Summary: Add your description here
Requires-Dist: beet>=0.113.0
Requires-Dist: bolt>=0.50.0
Requires-Dist: mecha>=0.102.0
Requires-Dist: aegis-core>=1.11.0 ; extra == 'aegis'
Requires-Dist: bolt-expressions>=0.17.0 ; extra == 'bolt-expressions'
Requires-Python: >=3.14
Provides-Extra: aegis
Provides-Extra: bolt-expressions
